mosaik/__init__.py
mosaik/_debug.py
mosaik/_version.py
mosaik/adapters.py
mosaik/async_scenario.py
mosaik/exceptions.py
mosaik/greetings_util.py
mosaik/in_or_out_set.py
mosaik/internal_util.py
mosaik/progress.py
mosaik/proxies.py
mosaik/py.typed
mosaik/scenario.py
mosaik/scheduler.py
mosaik/simmanager.py
mosaik/starters.py
mosaik/tiered_time.py
mosaik/util.py
mosaik/basic_simulators/__init__.py
mosaik/basic_simulators/input_simulator.py
mosaik/basic_simulators/output_simulator.py
mosaik-3.6.0.dist-info/METADATA
mosaik-3.6.0.dist-info/WHEEL
mosaik-3.6.0.dist-info/licenses/AUTHORS.rst
mosaik-3.6.0.dist-info/licenses/LICENSE.txt
mosaik-3.6.0.dist-info/RECORD
