Metadata-Version: 2.4
Name: mosaik
Version: 3.6.0
Summary: mosaik is a flexible smart-grid co-simulation framework
Project-URL: Homepage, https://mosaik.offis.de/
Project-URL: Repository, https://gitlab.com/mosaik/mosaik
Project-URL: Documentation, https://mosaik.readthedocs.io/
Project-URL: Discussions, https://github.com/orgs/OFFIS-mosaik/discussions
Author-email: mosaik development team <mosaik@offis.de>
License:                   GNU LESSER GENERAL PUBLIC LICENSE
License-File: AUTHORS.rst
License-File: LICENSE.txt
Classifier: Development Status :: 5 - Production/Stable
Classifier: Environment :: Console
Classifier: Intended Audience :: Science/Research
Classifier: Natural Language :: English
Classifier: Operating System :: OS Independent
Classifier: Topic :: Scientific/Engineering
Classifier: Topic :: Software Development :: Libraries :: Python Modules
Requires-Python: >=3.8
Requires-Dist: loguru>=0.6
Requires-Dist: mosaik-api-v3>=3.0.13
Requires-Dist: networkx>=2.5
Requires-Dist: tqdm>=4.66.4
Requires-Dist: typing-extensions>=4.11.0
